{
  "_comment": "Generated by scripts/fetch_market_prices.py. Lists races with ≥4pp moves over the last 2 day(s) (≈48h), sorted by largest single-outcome move.",
  "generated_at": "2026-07-11",
  "threshold_pp": 4,
  "window_days": 2,
  "window_label": "2d",
  "markets_fetched": 127,
  "suggestions": [
    {
      "market_id": "us-primary:AK:Senate",
      "slug": "vote-winner-in-alaska-senate-primary-final-round-20260630164517313",
      "category": "us_primary",
      "odds_format": "candidates",
      "min_pct": 3,
      "country_code": "US",
      "state_code": "AK",
      "city_code": null,
      "contest": "Senate Primary",
      "market_label": "Senate Primary",
      "party": null,
      "election_date": "2026-08-18",
      "election_title": "Democratic Senate Primary",
      "max_change_pp": 30.5,
      "changes": [
        {
          "name": "Dustin Darden",
          "current_pct": 19.5,
          "change_pp": 24.5,
          "direction": "down",
          "since_date": "2026-07-09",
          "reference_pct": 44.0,
          "change_days": 2,
          "window": "2d"
        },
        {
          "name": "Fred C. Grauberger",
          "current_pct": 22.0,
          "change_pp": 22.0,
          "direction": "down",
          "since_date": "2026-07-09",
          "reference_pct": 44.0,
          "change_days": 2,
          "window": "2d"
        },
        {
          "name": "Richard Grayson",
          "current_pct": 22.8,
          "change_pp": 21.2,
          "direction": "down",
          "since_date": "2026-07-09",
          "reference_pct": 44.0,
          "change_days": 2,
          "window": "2d"
        },
        {
          "name": "Carol Hafner",
          "current_pct": 19.5,
          "change_pp": 24.5,
          "direction": "down",
          "since_date": "2026-07-09",
          "reference_pct": 44.0,
          "change_days": 2,
          "window": "2d"
        },
        {
          "name": "Gerald L. Heikes",
          "current_pct": 19.0,
          "change_pp": 25.0,
          "direction": "down",
          "since_date": "2026-07-09",
          "reference_pct": 44.0,
          "change_days": 2,
          "window": "2d"
        },
        {
          "name": "Sid Hill",
          "current_pct": 19.5,
          "change_pp": 24.5,
          "direction": "down",
          "since_date": "2026-07-09",
          "reference_pct": 44.0,
          "change_days": 2,
          "window": "2d"
        },
        {
          "name": "Scott Kohlhaas",
          "current_pct": 29.0,
          "change_pp": 15.0,
          "direction": "down",
          "since_date": "2026-07-09",
          "reference_pct": 44.0,
          "change_days": 2,
          "window": "2d"
        },
        {
          "name": "Richard Benedict Mayers",
          "current_pct": 16.6,
          "change_pp": 27.4,
          "direction": "down",
          "since_date": "2026-07-09",
          "reference_pct": 44.0,
          "change_days": 2,
          "window": "2d"
        },
        {
          "name": "Heather McElwain",
          "current_pct": 13.5,
          "change_pp": 30.5,
          "direction": "down",
          "since_date": "2026-07-09",
          "reference_pct": 44.0,
          "change_days": 2,
          "window": "2d"
        },
        {
          "name": "Mary Peltola",
          "current_pct": 27.5,
          "change_pp": 16.5,
          "direction": "down",
          "since_date": "2026-07-09",
          "reference_pct": 44.0,
          "change_days": 2,
          "window": "2d"
        },
        {
          "name": "Reece Roberts",
          "current_pct": 19.5,
          "change_pp": 24.5,
          "direction": "down",
          "since_date": "2026-07-09",
          "reference_pct": 44.0,
          "change_days": 2,
          "window": "2d"
        },
        {
          "name": "Shirley Saucerman",
          "current_pct": 23.65,
          "change_pp": 20.35,
          "direction": "down",
          "since_date": "2026-07-09",
          "reference_pct": 44.0,
          "change_days": 2,
          "window": "2d"
        },
        {
          "name": "Earl D. \"Skip\" Southworth",
          "current_pct": 19.5,
          "change_pp": 24.5,
          "direction": "down",
          "since_date": "2026-07-09",
          "reference_pct": 44.0,
          "change_days": 2,
          "window": "2d"
        },
        {
          "name": "Dan J. Sullivan",
          "current_pct": 17.5,
          "change_pp": 17.5,
          "direction": "down",
          "since_date": "2026-07-09",
          "reference_pct": 35.0,
          "change_days": 2,
          "window": "2d"
        },
        {
          "name": "Sen. Dan S. Sullivan",
          "current_pct": 26.1,
          "change_pp": 17.9,
          "direction": "down",
          "since_date": "2026-07-09",
          "reference_pct": 44.0,
          "change_days": 2,
          "window": "2d"
        }
      ],
      "prices": [
        {
          "name": "David Leslie",
          "current_pct": 44.1
        },
        {
          "name": "Scott Kohlhaas",
          "current_pct": 29.0,
          "change_pp": 15.0,
          "direction": "down",
          "since_date": "2026-07-09",
          "reference_pct": 44.0,
          "change_days": 2,
          "window": "2d"
        },
        {
          "name": "Mary Peltola",
          "current_pct": 27.5,
          "change_pp": 16.5,
          "direction": "down",
          "since_date": "2026-07-09",
          "reference_pct": 44.0,
          "change_days": 2,
          "window": "2d"
        },
        {
          "name": "Sen. Dan S. Sullivan",
          "current_pct": 26.1,
          "change_pp": 17.9,
          "direction": "down",
          "since_date": "2026-07-09",
          "reference_pct": 44.0,
          "change_days": 2,
          "window": "2d"
        },
        {
          "name": "Shirley Saucerman",
          "current_pct": 23.65,
          "change_pp": 20.35,
          "direction": "down",
          "since_date": "2026-07-09",
          "reference_pct": 44.0,
          "change_days": 2,
          "window": "2d"
        },
        {
          "name": "Richard Grayson",
          "current_pct": 22.8,
          "change_pp": 21.2,
          "direction": "down",
          "since_date": "2026-07-09",
          "reference_pct": 44.0,
          "change_days": 2,
          "window": "2d"
        },
        {
          "name": "Fred C. Grauberger",
          "current_pct": 22.0,
          "change_pp": 22.0,
          "direction": "down",
          "since_date": "2026-07-09",
          "reference_pct": 44.0,
          "change_days": 2,
          "window": "2d"
        },
        {
          "name": "Dustin Darden",
          "current_pct": 19.5,
          "change_pp": 24.5,
          "direction": "down",
          "since_date": "2026-07-09",
          "reference_pct": 44.0,
          "change_days": 2,
          "window": "2d"
        },
        {
          "name": "Carol Hafner",
          "current_pct": 19.5,
          "change_pp": 24.5,
          "direction": "down",
          "since_date": "2026-07-09",
          "reference_pct": 44.0,
          "change_days": 2,
          "window": "2d"
        },
        {
          "name": "Sid Hill",
          "current_pct": 19.5,
          "change_pp": 24.5,
          "direction": "down",
          "since_date": "2026-07-09",
          "reference_pct": 44.0,
          "change_days": 2,
          "window": "2d"
        },
        {
          "name": "Reece Roberts",
          "current_pct": 19.5,
          "change_pp": 24.5,
          "direction": "down",
          "since_date": "2026-07-09",
          "reference_pct": 44.0,
          "change_days": 2,
          "window": "2d"
        },
        {
          "name": "Earl D. \"Skip\" Southworth",
          "current_pct": 19.5,
          "change_pp": 24.5,
          "direction": "down",
          "since_date": "2026-07-09",
          "reference_pct": 44.0,
          "change_days": 2,
          "window": "2d"
        },
        {
          "name": "Gerald L. Heikes",
          "current_pct": 19.0,
          "change_pp": 25.0,
          "direction": "down",
          "since_date": "2026-07-09",
          "reference_pct": 44.0,
          "change_days": 2,
          "window": "2d"
        },
        {
          "name": "Dan J. Sullivan",
          "current_pct": 17.5,
          "change_pp": 17.5,
          "direction": "down",
          "since_date": "2026-07-09",
          "reference_pct": 35.0,
          "change_days": 2,
          "window": "2d"
        },
        {
          "name": "Richard Benedict Mayers",
          "current_pct": 16.6,
          "change_pp": 27.4,
          "direction": "down",
          "since_date": "2026-07-09",
          "reference_pct": 44.0,
          "change_days": 2,
          "window": "2d"
        },
        {
          "name": "Heather McElwain",
          "current_pct": 13.5,
          "change_pp": 30.5,
          "direction": "down",
          "since_date": "2026-07-09",
          "reference_pct": 44.0,
          "change_days": 2,
          "window": "2d"
        }
      ]
    },
    {
      "market_id": "us-primary:AK:Governor",
      "slug": "who-will-advance-from-the-alaska-governor-primary",
      "category": "us_primary",
      "odds_format": "candidates",
      "min_pct": 3,
      "country_code": "US",
      "state_code": "AK",
      "city_code": null,
      "contest": "Governor Primary",
      "market_label": "Governor Primary",
      "party": null,
      "election_date": "2026-08-18",
      "election_title": "Democratic Governor Primary",
      "max_change_pp": 30.0,
      "changes": [
        {
          "name": "Lesil McGuire",
          "current_pct": 9.5,
          "change_pp": 21.0,
          "direction": "down",
          "since_date": "2026-07-09",
          "reference_pct": 30.5,
          "change_days": 2,
          "window": "2d"
        },
        {
          "name": "Bill Walker",
          "current_pct": 55.0,
          "change_pp": 30.0,
          "direction": "up",
          "since_date": "2026-07-09",
          "reference_pct": 25.0,
          "change_days": 2,
          "window": "2d"
        }
      ],
      "prices": [
        {
          "name": "Tom Begich",
          "current_pct": 95.3
        },
        {
          "name": "Bernadette Wilson",
          "current_pct": 71.0
        },
        {
          "name": "Jonathan Kreiss-Tomkins",
          "current_pct": 64.0
        },
        {
          "name": "Bill Walker",
          "current_pct": 55.0,
          "change_pp": 30.0,
          "direction": "up",
          "since_date": "2026-07-09",
          "reference_pct": 25.0,
          "change_days": 2,
          "window": "2d"
        },
        {
          "name": "Dave Bronson",
          "current_pct": 43.0
        },
        {
          "name": "Click Bishop",
          "current_pct": 41.0
        },
        {
          "name": "Treg Taylor",
          "current_pct": 12.5
        },
        {
          "name": "Lesil McGuire",
          "current_pct": 9.5,
          "change_pp": 21.0,
          "direction": "down",
          "since_date": "2026-07-09",
          "reference_pct": 30.5,
          "change_days": 2,
          "window": "2d"
        },
        {
          "name": "Adam Crum",
          "current_pct": 7.5
        },
        {
          "name": "Matt Heilala",
          "current_pct": 4.55
        },
        {
          "name": "Shelley Hughes",
          "current_pct": 4.15
        }
      ]
    },
    {
      "market_id": "us-primary:RI:Governor:Republican",
      "slug": "rhode-island-governor-republican-primary-winner",
      "category": "us_primary",
      "odds_format": "candidates",
      "min_pct": 3,
      "country_code": "US",
      "state_code": "RI",
      "city_code": null,
      "contest": "Republican Governor Primary",
      "market_label": "Republican Governor Primary",
      "party": "Republican",
      "election_date": "2026-09-09",
      "election_title": "Democratic Governor Primary",
      "max_change_pp": 26.15,
      "changes": [
        {
          "name": "Aaron Guckian",
          "current_pct": 19.1,
          "change_pp": 26.15,
          "direction": "down",
          "since_date": "2026-07-09",
          "reference_pct": 45.25,
          "change_days": 2,
          "window": "2d"
        },
        {
          "name": "Elaine Pelino",
          "current_pct": 67.0,
          "change_pp": 10.5,
          "direction": "up",
          "since_date": "2026-07-09",
          "reference_pct": 56.5,
          "change_days": 2,
          "window": "2d"
        }
      ],
      "prices": [
        {
          "name": "Elaine Pelino",
          "current_pct": 67.0,
          "change_pp": 10.5,
          "direction": "up",
          "since_date": "2026-07-09",
          "reference_pct": 56.5,
          "change_days": 2,
          "window": "2d"
        },
        {
          "name": "Aaron Guckian",
          "current_pct": 19.1,
          "change_pp": 26.15,
          "direction": "down",
          "since_date": "2026-07-09",
          "reference_pct": 45.25,
          "change_days": 2,
          "window": "2d"
        }
      ]
    },
    {
      "market_id": "us-primary:MN:Governor:Republican",
      "slug": "minnesota-governor-republican-primary-winner",
      "category": "us_primary",
      "odds_format": "candidates",
      "min_pct": 3,
      "country_code": "US",
      "state_code": "MN",
      "city_code": null,
      "contest": "Republican Governor Primary",
      "market_label": "Republican Governor Primary",
      "party": "Republican",
      "election_date": "2026-08-11",
      "election_title": "Democratic Governor Primary",
      "max_change_pp": 11.5,
      "changes": [
        {
          "name": "Mike Lindell",
          "current_pct": 25.0,
          "change_pp": 11.5,
          "direction": "down",
          "since_date": "2026-07-09",
          "reference_pct": 36.5,
          "change_days": 2,
          "window": "2d"
        }
      ],
      "prices": [
        {
          "name": "Lisa Demuth",
          "current_pct": 37.5
        },
        {
          "name": "Kendall Qualls",
          "current_pct": 29.0
        },
        {
          "name": "Mike Lindell",
          "current_pct": 25.0,
          "change_pp": 11.5,
          "direction": "down",
          "since_date": "2026-07-09",
          "reference_pct": 36.5,
          "change_days": 2,
          "window": "2d"
        }
      ]
    },
    {
      "market_id": "national:SE:Riksdag:prime_minister",
      "slug": "next-prime-minister-of-sweden",
      "category": "national",
      "odds_format": "candidates",
      "min_pct": 3,
      "country_code": "SE",
      "state_code": null,
      "city_code": null,
      "contest": "Riksdag",
      "market_label": "Next Prime Minister",
      "party": null,
      "election_date": "2026-09-13",
      "election_title": "Riksdag",
      "max_change_pp": 7.5,
      "changes": [
        {
          "name": "Ulf Kristersson",
          "current_pct": 14.0,
          "change_pp": 6.0,
          "direction": "down",
          "since_date": "2026-07-09",
          "reference_pct": 20.0,
          "change_days": 2,
          "window": "2d"
        },
        {
          "name": "Magdalena Andersson",
          "current_pct": 81.0,
          "change_pp": 7.5,
          "direction": "up",
          "since_date": "2026-07-09",
          "reference_pct": 73.5,
          "change_days": 2,
          "window": "2d"
        }
      ],
      "prices": [
        {
          "name": "Magdalena Andersson",
          "current_pct": 81.0,
          "change_pp": 7.5,
          "direction": "up",
          "since_date": "2026-07-09",
          "reference_pct": 73.5,
          "change_days": 2,
          "window": "2d"
        },
        {
          "name": "Ulf Kristersson",
          "current_pct": 14.0,
          "change_pp": 6.0,
          "direction": "down",
          "since_date": "2026-07-09",
          "reference_pct": 20.0,
          "change_days": 2,
          "window": "2d"
        }
      ]
    },
    {
      "market_id": "national:NZ:Parliament:prime_minister",
      "slug": "next-prime-minister-of-new-zealand-174",
      "category": "national",
      "odds_format": "candidates",
      "min_pct": 3,
      "country_code": "NZ",
      "state_code": null,
      "city_code": null,
      "contest": "Parliament",
      "market_label": "Next Prime Minister",
      "party": null,
      "election_date": "2026-11-07",
      "election_title": "Parliament",
      "max_change_pp": 6.5,
      "changes": [
        {
          "name": "Chris Hipkins",
          "current_pct": 44.5,
          "change_pp": 6.5,
          "direction": "up",
          "since_date": "2026-07-09",
          "reference_pct": 38.0,
          "change_days": 2,
          "window": "2d"
        }
      ],
      "prices": [
        {
          "name": "Christopher Luxon",
          "current_pct": 44.5
        },
        {
          "name": "Chris Hipkins",
          "current_pct": 44.5,
          "change_pp": 6.5,
          "direction": "up",
          "since_date": "2026-07-09",
          "reference_pct": 38.0,
          "change_days": 2,
          "window": "2d"
        },
        {
          "name": "Nicola Willis",
          "current_pct": 5.05
        },
        {
          "name": "Winston Peters",
          "current_pct": 3.1
        }
      ]
    },
    {
      "market_id": "de-state:BE",
      "slug": "berlin-state-election-winner",
      "category": "de_state",
      "odds_format": "party",
      "min_pct": 10,
      "country_code": "DE",
      "state_code": "BE",
      "city_code": null,
      "contest": "Abgeordnetenhaus",
      "market_label": "Abgeordnetenhaus",
      "party": null,
      "election_date": "2026-09-20",
      "election_title": "State",
      "max_change_pp": 5.0,
      "changes": [
        {
          "name": "CDU",
          "current_pct": 19.5,
          "change_pp": 5.0,
          "direction": "down",
          "since_date": "2026-07-09",
          "reference_pct": 24.5,
          "change_days": 2,
          "window": "2d"
        },
        {
          "name": "Linke",
          "current_pct": 34.5,
          "change_pp": 5.0,
          "direction": "up",
          "since_date": "2026-07-09",
          "reference_pct": 29.5,
          "change_days": 2,
          "window": "2d"
        }
      ],
      "prices": [
        {
          "name": "Linke",
          "current_pct": 34.5,
          "change_pp": 5.0,
          "direction": "up",
          "since_date": "2026-07-09",
          "reference_pct": 29.5,
          "change_days": 2,
          "window": "2d"
        },
        {
          "name": "AfD",
          "current_pct": 21.85
        },
        {
          "name": "Grüne",
          "current_pct": 20.25
        },
        {
          "name": "CDU",
          "current_pct": 19.5,
          "change_pp": 5.0,
          "direction": "down",
          "since_date": "2026-07-09",
          "reference_pct": 24.5,
          "change_days": 2,
          "window": "2d"
        }
      ]
    },
    {
      "market_id": "us-governor:NH",
      "slug": "new-hampshire-governor-winner-2026",
      "category": "us_governor",
      "odds_format": "party",
      "min_pct": 3,
      "country_code": "US",
      "state_code": "NH",
      "city_code": null,
      "contest": "Governor",
      "market_label": null,
      "party": null,
      "election_date": "2026-09-08",
      "election_title": "Democratic Governor Primary",
      "max_change_pp": 5.0,
      "changes": [
        {
          "name": "Republican",
          "current_pct": 77.5,
          "change_pp": 5.0,
          "direction": "up",
          "since_date": "2026-07-09",
          "reference_pct": 72.5,
          "change_days": 2,
          "window": "2d"
        }
      ],
      "prices": [
        {
          "name": "Republican",
          "current_pct": 77.5,
          "change_pp": 5.0,
          "direction": "up",
          "since_date": "2026-07-09",
          "reference_pct": 72.5,
          "change_days": 2,
          "window": "2d"
        },
        {
          "name": "Democrat",
          "current_pct": 22.0
        }
      ]
    },
    {
      "market_id": "us-primary:WI:Governor:Democratic",
      "slug": "wisconsin-governor-democratic-primary-winner",
      "category": "us_primary",
      "odds_format": "candidates",
      "min_pct": 3,
      "country_code": "US",
      "state_code": "WI",
      "city_code": null,
      "contest": "Democratic Governor Primary",
      "market_label": "Democratic Governor Primary",
      "party": "Democratic",
      "election_date": "2026-08-11",
      "election_title": "Democratic Governor Primary",
      "max_change_pp": 5.0,
      "changes": [
        {
          "name": "Mandela Barnes",
          "current_pct": 12.0,
          "change_pp": 5.0,
          "direction": "down",
          "since_date": "2026-07-09",
          "reference_pct": 17.0,
          "change_days": 2,
          "window": "2d"
        }
      ],
      "prices": [
        {
          "name": "Francesca Hong",
          "current_pct": 50.75
        },
        {
          "name": "Sara Rodriguez",
          "current_pct": 32.0
        },
        {
          "name": "Mandela Barnes",
          "current_pct": 12.0,
          "change_pp": 5.0,
          "direction": "down",
          "since_date": "2026-07-09",
          "reference_pct": 17.0,
          "change_days": 2,
          "window": "2d"
        }
      ]
    },
    {
      "market_id": "us-primary:NH:Senate:Democratic",
      "slug": "new-hampshire-democratic-senate-primary-winner",
      "category": "us_primary",
      "odds_format": "candidates",
      "min_pct": 3,
      "country_code": "US",
      "state_code": "NH",
      "city_code": null,
      "contest": "Democratic Senate Primary",
      "market_label": "Democratic Senate Primary",
      "party": "Democratic",
      "election_date": "2026-09-08",
      "election_title": "Democratic Senate Primary",
      "max_change_pp": 4.8,
      "changes": [
        {
          "name": "Karishma Manzur",
          "current_pct": 7.0,
          "change_pp": 4.8,
          "direction": "down",
          "since_date": "2026-07-09",
          "reference_pct": 11.8,
          "change_days": 2,
          "window": "2d"
        }
      ],
      "prices": [
        {
          "name": "Chris Pappas",
          "current_pct": 91.5
        },
        {
          "name": "Karishma Manzur",
          "current_pct": 7.0,
          "change_pp": 4.8,
          "direction": "down",
          "since_date": "2026-07-09",
          "reference_pct": 11.8,
          "change_days": 2,
          "window": "2d"
        }
      ]
    },
    {
      "market_id": "us-primary:KS:Governor:Republican",
      "slug": "kansas-governor-republican-primary-winner",
      "category": "us_primary",
      "odds_format": "candidates",
      "min_pct": 3,
      "country_code": "US",
      "state_code": "KS",
      "city_code": null,
      "contest": "Republican Governor Primary",
      "market_label": "Republican Governor Primary",
      "party": "Republican",
      "election_date": "2026-08-04",
      "election_title": "Democratic Governor Primary",
      "max_change_pp": 4.55,
      "changes": [
        {
          "name": "Philip Sarnecki",
          "current_pct": 6.35,
          "change_pp": 4.55,
          "direction": "up",
          "since_date": "2026-07-09",
          "reference_pct": 1.8,
          "change_days": 2,
          "window": "2d"
        }
      ],
      "prices": [
        {
          "name": "Ty Masterson",
          "current_pct": 90.5
        },
        {
          "name": "Philip Sarnecki",
          "current_pct": 6.35,
          "change_pp": 4.55,
          "direction": "up",
          "since_date": "2026-07-09",
          "reference_pct": 1.8,
          "change_days": 2,
          "window": "2d"
        },
        {
          "name": "Vicki Schmidt",
          "current_pct": 3.55
        }
      ]
    },
    {
      "market_id": "us-governor:AK",
      "slug": "alaska-governor-election-winner",
      "category": "us_governor",
      "odds_format": "candidates",
      "min_pct": 3,
      "country_code": "US",
      "state_code": "AK",
      "city_code": null,
      "contest": "Governor",
      "market_label": null,
      "party": null,
      "election_date": "2026-08-18",
      "election_title": "Democratic Governor Primary",
      "max_change_pp": 4.5,
      "changes": [
        {
          "name": "Tom Begich",
          "current_pct": 30.0,
          "change_pp": 4.5,
          "direction": "up",
          "since_date": "2026-07-09",
          "reference_pct": 25.5,
          "change_days": 2,
          "window": "2d"
        }
      ],
      "prices": [
        {
          "name": "Tom Begich",
          "current_pct": 30.0,
          "change_pp": 4.5,
          "direction": "up",
          "since_date": "2026-07-09",
          "reference_pct": 25.5,
          "change_days": 2,
          "window": "2d"
        },
        {
          "name": "Bernadette Wilson",
          "current_pct": 20.5
        },
        {
          "name": "Jonathan Kreiss-Tomkins",
          "current_pct": 17.7
        },
        {
          "name": "Treg Taylor",
          "current_pct": 11.05
        },
        {
          "name": "Bill Walker",
          "current_pct": 6.95
        },
        {
          "name": "David Bronson",
          "current_pct": 6.1
        },
        {
          "name": "Click Bishop",
          "current_pct": 5.7
        }
      ]
    },
    {
      "market_id": "us-primary:KS:Governor:Democratic",
      "slug": "kansas-governor-democratic-primary-winner",
      "category": "us_primary",
      "odds_format": "candidates",
      "min_pct": 3,
      "country_code": "US",
      "state_code": "KS",
      "city_code": null,
      "contest": "Democratic Governor Primary",
      "market_label": "Democratic Governor Primary",
      "party": "Democratic",
      "election_date": "2026-08-04",
      "election_title": "Democratic Governor Primary",
      "max_change_pp": 4.5,
      "changes": [
        {
          "name": "Ethan Corson",
          "current_pct": 29.0,
          "change_pp": 4.5,
          "direction": "down",
          "since_date": "2026-07-09",
          "reference_pct": 33.5,
          "change_days": 2,
          "window": "2d"
        }
      ],
      "prices": [
        {
          "name": "Cindy Holscher",
          "current_pct": 67.5
        },
        {
          "name": "Ethan Corson",
          "current_pct": 29.0,
          "change_pp": 4.5,
          "direction": "down",
          "since_date": "2026-07-09",
          "reference_pct": 33.5,
          "change_days": 2,
          "window": "2d"
        }
      ]
    },
    {
      "market_id": "us-governor:KS",
      "slug": "kansas-governor-winner-2026",
      "category": "us_governor",
      "odds_format": "party",
      "min_pct": 3,
      "country_code": "US",
      "state_code": "KS",
      "city_code": null,
      "contest": "Governor",
      "market_label": null,
      "party": null,
      "election_date": "2026-08-04",
      "election_title": "Democratic Governor Primary",
      "max_change_pp": 4.0,
      "changes": [
        {
          "name": "Democrat",
          "current_pct": 33.0,
          "change_pp": 4.0,
          "direction": "up",
          "since_date": "2026-07-09",
          "reference_pct": 29.0,
          "change_days": 2,
          "window": "2d"
        }
      ],
      "prices": [
        {
          "name": "Republican",
          "current_pct": 65.5
        },
        {
          "name": "Democrat",
          "current_pct": 33.0,
          "change_pp": 4.0,
          "direction": "up",
          "since_date": "2026-07-09",
          "reference_pct": 29.0,
          "change_days": 2,
          "window": "2d"
        }
      ]
    },
    {
      "market_id": "us-primary:TN:Governor:Democratic",
      "slug": "tennessee-governor-democratic-primary-winner",
      "category": "us_primary",
      "odds_format": "candidates",
      "min_pct": 3,
      "country_code": "US",
      "state_code": "TN",
      "city_code": null,
      "contest": "Democratic Governor Primary",
      "market_label": "Democratic Governor Primary",
      "party": "Democratic",
      "election_date": "2026-08-06",
      "election_title": "Democratic Governor Primary",
      "max_change_pp": 4.0,
      "changes": [
        {
          "name": "Carnita Atwater",
          "current_pct": 10.0,
          "change_pp": 4.0,
          "direction": "up",
          "since_date": "2026-07-09",
          "reference_pct": 6.0,
          "change_days": 2,
          "window": "2d"
        }
      ],
      "prices": [
        {
          "name": "Jerri Green",
          "current_pct": 84.5
        },
        {
          "name": "Carnita Atwater",
          "current_pct": 10.0,
          "change_pp": 4.0,
          "direction": "up",
          "since_date": "2026-07-09",
          "reference_pct": 6.0,
          "change_days": 2,
          "window": "2d"
        }
      ]
    },
    {
      "market_id": "us-senate:KS",
      "slug": "kansas-senate-election-winner",
      "category": "us_senate",
      "odds_format": "party",
      "min_pct": 3,
      "country_code": "US",
      "state_code": "KS",
      "city_code": null,
      "contest": "Senate",
      "market_label": null,
      "party": null,
      "election_date": "2026-08-04",
      "election_title": "Democratic Senate Primary",
      "max_change_pp": 4.0,
      "changes": [
        {
          "name": "Republican",
          "current_pct": 80.0,
          "change_pp": 4.0,
          "direction": "down",
          "since_date": "2026-07-09",
          "reference_pct": 84.0,
          "change_days": 2,
          "window": "2d"
        }
      ],
      "prices": [
        {
          "name": "Republican",
          "current_pct": 80.0,
          "change_pp": 4.0,
          "direction": "down",
          "since_date": "2026-07-09",
          "reference_pct": 84.0,
          "change_days": 2,
          "window": "2d"
        },
        {
          "name": "Democrat",
          "current_pct": 18.0
        }
      ]
    }
  ]
}
